[
  {
    "type": "material",
    "ident": "osrs_bronze",
    "name": "Bronze",
    "density": 9,
    "specific_heat_liquid": 1.18,
    "specific_heat_solid": 0.91,
    "latent_heat": 398,
    "bash_resist": 0,
    "cut_resist": 4,
    "acid_resist": 4,
    "fire_resist": 2,
    "elec_resist": 0,
    "chip_resist": 10,
    "repaired_with": "material_osrs_bronze_bar",
    "dmg_adj": [ "dented", "bent", "smashed", "destroyed" ],
    "bash_dmg_verb": "dented",
    "cut_dmg_verb": "scratched",
    "compacts_into": [ "material_osrs_bronze_bar" ]
  },
  {
    "type": "material",
    "ident": "osrs_iron",
    "name": "Iron",
    "density": 9,
    "specific_heat_liquid": 1.18,
    "specific_heat_solid": 0.91,
    "latent_heat": 398,
    "bash_resist": 0,
    "cut_resist": 4,
    "acid_resist": 4,
    "fire_resist": 2,
    "elec_resist": 0,
    "chip_resist": 10,
    "repaired_with": "material_osrs_iron_bar",
    "dmg_adj": [ "dented", "bent", "smashed", "destroyed" ],
    "bash_dmg_verb": "dented",
    "cut_dmg_verb": "scratched",
    "compacts_into": [ "material_osrs_iron_bar" ]
  }
]